generator_cucumber/__init__.py
generator_cucumber/__main__.py
generator_cucumber/_version.py
generator_cucumber/allure_generator.py
generator_cucumber/api_github.py
generator_cucumber/api_gitlab.py
generator_cucumber/bdd_generator.py
generator_cucumber/cache_file.py
generator_cucumber/create_file.py
generator_cucumber/cucumber_text.py
generator_cucumber/generator.py
generator_cucumber-0.0.23.dist-info/LICENSE
generator_cucumber-0.0.23.dist-info/METADATA
generator_cucumber-0.0.23.dist-info/WHEEL
generator_cucumber-0.0.23.dist-info/entry_points.txt
generator_cucumber-0.0.23.dist-info/top_level.txt
generator_cucumber-0.0.23.dist-info/RECORD
