Metadata-Version: 2.1
Name: generator_cucumber
Version: 0.0.23
Summary: Generation gitlab/github => .feature file
Author-email: Dmitry Shibikin <dmitry.shibikin@yandex.ru>
License: The MIT License (MIT)
Project-URL: Repository, https://gitlab.com/python_lib/generator_cucumber
Project-URL: Homepage, https://gitlab.com/python_lib/generator_cucumber
Project-URL: Documentation, https://bdd-generator.readthedocs.io/ru/latest/
Keywords: python,cucmber,generator
Classifier: License :: OSI Approved :: MIT License
Classifier: Intended Audience :: Developers
Classifier: Operating System :: Unix
Classifier: Programming Language :: Python :: 3.8
Classifier: Topic :: Software Development :: Libraries
Classifier: Topic :: Utilities
Requires-Python: >=3.8
License-File: LICENSE
